noisepy/seis/io/__init__.py
noisepy/seis/io/_version.py
noisepy/seis/io/asdfstore.py
noisepy/seis/io/channel_filter_store.py
noisepy/seis/io/channelcatalog.py
noisepy/seis/io/compositerawstore.py
noisepy/seis/io/constants.py
noisepy/seis/io/datatypes.py
noisepy/seis/io/h5store.py
noisepy/seis/io/hierarchicalstores.py
noisepy/seis/io/mseedstore.py
noisepy/seis/io/numpystore.py
noisepy/seis/io/plotting_modules.py
noisepy/seis/io/pnwstore.py
noisepy/seis/io/s3store.py
noisepy/seis/io/stores.py
noisepy/seis/io/tiledb.py
noisepy/seis/io/utils.py
noisepy/seis/io/zarrstore.py
noisepy_seis_io-0.3.3.dist-info/METADATA
noisepy_seis_io-0.3.3.dist-info/WHEEL
noisepy_seis_io-0.3.3.dist-info/licenses/LICENSE
noisepy_seis_io-0.3.3.dist-info/RECORD
