Metadata-Version: 2.4
Name: noisepy-seis-io
Version: 0.3.3
Project-URL: Homepage, https://github.com/noisepy/noisepy-io
Author-email: Marine Denolle <mdenolle@uw.edu>, Carlos Suarez <carlosg@uw.edu>, Ishika Khandelwal <ishikakhandelwal02@gmail.com>, Yiyu Ni <niyiyu@uw.edu>
License: MIT License
License-File: LICENSE
Classifier: Development Status :: 4 - Beta
Classifier: Intended Audience :: Developers
Classifier: Intended Audience :: Science/Research
Classifier: License :: OSI Approved :: MIT License
Classifier: Operating System :: OS Independent
Classifier: Programming Language :: Python
Requires-Dist: datetimerange<3.0.0,>=2.0.0
Requires-Dist: diskcache
Requires-Dist: fsspec<2024.0.0,>=2023.4.0
Requires-Dist: numcodecs<0.16.0
Requires-Dist: numpy<2.0.0,>=1.22.0
Requires-Dist: pandas<2.0.0,>=1.5.3
Requires-Dist: psutil<6.0.0,>=5.9.5
Requires-Dist: pyasdf<1.0.0,>=0.7.5
Requires-Dist: pydantic-yaml==1.0
Requires-Dist: pydantic==2.3.0
Requires-Dist: pyyaml==6.0
Requires-Dist: s3fs<2024.0.0,==2023.4.0
Requires-Dist: tqdm
Requires-Dist: zarr==2.14.2
Provides-Extra: dev
Requires-Dist: black; extra == 'dev'
Requires-Dist: ipython; extra == 'dev'
Requires-Dist: matplotlib; extra == 'dev'
Requires-Dist: nbconvert; extra == 'dev'
Requires-Dist: nbsphinx; extra == 'dev'
Requires-Dist: numpy; extra == 'dev'
Requires-Dist: pre-commit; extra == 'dev'
Requires-Dist: pytest; extra == 'dev'
Requires-Dist: pytest-cov; extra == 'dev'
Requires-Dist: sphinx; extra == 'dev'
Requires-Dist: sphinx-autoapi; extra == 'dev'
Requires-Dist: sphinx-rtd-theme; extra == 'dev'
